{
  "schemaVersion": 1,
  "paused": false,
  "currentPhase": "A",
  "currentStep": 8,
  "attempt": 1,
  "phaseAttemptsTotal": 1,
  "budget": { "softCapUsd": 50, "hardCapUsd": 150, "spentUsd": 0 },
  "approvals": {
    "pending": null,
    "granted": [
      {
        "action": "sst deploy --stage production (A.1)",
        "blastRadius": "Updated basics-worker ECS task def env block (additive); revision :14",
        "at": "2026-05-13T00:00:00Z",
        "autoGranted": true
      },
      {
        "action": "sst deploy --stage production (A.2)",
        "blastRadius": "Created SES config set basics-runtime-outbound, SNS topic basics-ses-events, event destination, worker SES IAM policy; existing SES identity untouched",
        "at": "2026-05-13T01:00:00Z",
        "autoGranted": true
      },
      {
        "action": "apply_migration automations_a3_output_quotas (A.3)",
        "blastRadius": "Additive: new public.workspace_output_quotas table with RLS, new SECURITY DEFINER function increment_output_quota",
        "at": "2026-05-13T01:15:00Z",
        "autoGranted": true
      }
    ]
  },
  "lastFailure": null,
  "blocked": null,
  "killSwitch": { "paused": false, "emergencyHalt": false },
  "history": [
    {
      "phase": "A",
      "step": "A.1",
      "attempt": 1,
      "status": "passed",
      "at": "2026-05-13T00:00:00Z",
      "evidence": "docs/.automation-loop/artifacts/A/A.1/{sst-deploy.log,task-def-after.json,verify.log}",
      "summary": "Wired SENDBLUE/SES/ARTIFACTS env into basics-worker task def revision :14."
    },
    {
      "phase": "A",
      "step": "A.2",
      "attempt": 1,
      "status": "failed",
      "at": "2026-05-13T00:30:00Z",
      "evidence": "docs/.automation-loop/artifacts/A/A.2/sst-deploy.log",
      "summary": "Pulumi maxDeliverySeconds=0 default rejected by SES (needs >=300)."
    },
    {
      "phase": "A",
      "step": "A.2",
      "attempt": 2,
      "status": "passed",
      "at": "2026-05-13T01:00:00Z",
      "evidence": "docs/.automation-loop/artifacts/A/A.2/{...}",
      "summary": "Option A: ref existing SES identity via data source; created NEW basics-runtime-outbound config set, basics-ses-events SNS topic, event destination, worker SES IAM policy."
    },
    {
      "phase": "A",
      "step": "A.3",
      "attempt": 1,
      "status": "passed",
      "at": "2026-05-13T01:15:00Z",
      "evidence": "docs/.automation-loop/artifacts/A/A.3/{...} + api/drizzle/0020_workspace_output_quotas.sql",
      "summary": "workspace_output_quotas + increment_output_quota; fixture cap=2 returned [true,true,false]."
    },
    {
      "phase": "A",
      "step": "A.4",
      "attempt": 1,
      "status": "passed",
      "at": "2026-05-13T01:30:00Z",
      "evidence": "docs/.automation-loop/artifacts/A/A.4/{...}",
      "summary": "shared/src/activity.ts: output_dispatched/output_failed Zod schemas + discriminated union.",
      "reviewerVerdict": "ship"
    },
    {
      "phase": "A",
      "step": "A.5",
      "attempt": 1,
      "status": "passed",
      "at": "2026-05-13T01:45:00Z",
      "evidence": "docs/.automation-loop/artifacts/A/A.5/{...}",
      "summary": "attach_artifact tool; 10 unit tests + live S3 round-trip OK.",
      "reviewerVerdict": "ship"
    },
    {
      "phase": "A",
      "step": "A.6",
      "attempt": 1,
      "status": "passed",
      "at": "2026-05-13T02:00:00Z",
      "evidence": "docs/.automation-loop/artifacts/A/A.6/{...}",
      "summary": "send_email tool (SESv2 + QuotaStore). Cycle 1 caught header-injection blockers (CRLF in subject/filename); cycle 2 ship after Zod refines + base64 body. Live e2e MessageId returned.",
      "reviewerVerdict": "ship"
    },
    {
      "phase": "A",
      "step": "A.7",
      "attempt": 1,
      "status": "passed",
      "at": "2026-05-13T02:15:00Z",
      "evidence": "docs/.automation-loop/artifacts/A/A.7/{test.log,tsc.log,verify.log,e2e-send.log,review-1.json}",
      "summary": "send_sms tool via Sendblue direct-auth headers + injectable summarizer. 11/11 unit tests cover iMessage / SMS-fallback / summary-on-downgrade / summary-failure / quota / 4xx / E.164 validation. Live Sendblue send DEFERRED (no local secret access + no operator phone) — A.9 smoke will cover.",
      "reviewerVerdict": "ship"
    }
  ],
  "completed": false,
  "deferredVerifications": [
    {
      "step": "A.7",
      "what": "Live Sendblue send to operator's E.164 phone with delivery confirmation via GET /api/messages/:id",
      "blocker_for_now": false,
      "covered_by": "A.9 smoke e2e (chat-driven run that exercises send_sms end-to-end)",
      "operator_action": "Confirm SENDBLUE_API_KEY/SECRET still valid in production worker; supply phone number when A.9 runs."
    }
  ],
  "operatorDecisions": [
    {
      "step": "A.2",
      "at": "2026-05-13T00:45:00Z",
      "decision": "Option A (codify-as-is)",
      "by": "user (chat reply)"
    },
    {
      "step": "global",
      "at": "2026-05-13T01:00:00Z",
      "decision": "No git push between loop iterations",
      "by": "user (chat reply)"
    },
    {
      "step": "A.3",
      "at": "2026-05-13T01:20:00Z",
      "decision": "Mirror MCP migrations to api/drizzle/",
      "by": "user (chat reply)"
    }
  ]
}
